mdscraper/__init__.py
mdscraper/cli.py
mdscraper/core/__init__.py
mdscraper/core/scraper.py
mdscraper/core/utils.py
mdscraper-0.1.3.dist-info/licenses/LICENSE
mdscraper-0.1.3.dist-info/METADATA
mdscraper-0.1.3.dist-info/WHEEL
mdscraper-0.1.3.dist-info/entry_points.txt
mdscraper-0.1.3.dist-info/top_level.txt
mdscraper-0.1.3.dist-info/RECORD
