Metadata-Version: 2.4
Name: mdscraper
Version: 0.1.3
Summary: A tool to fetch webpages and convert their content to clean Markdown format for LLM processing
Author-email: Oscar Jiang <pengj0520@gmail.com>
License-Expression: MIT
Project-URL: Homepage, https://github.com/warmwind/mdscraper
Project-URL: Bug Tracker, https://github.com/warmwind/mdscraper/issues
Classifier: Development Status :: 4 - Beta
Classifier: Intended Audience :: Developers
Classifier: Topic :: Text Processing :: Markup
Classifier: Topic :: Internet :: WWW/HTTP :: Dynamic Content
Classifier: Programming Language :: Python :: 3
Classifier: Programming Language :: Python :: 3.7
Classifier: Programming Language :: Python :: 3.8
Classifier: Programming Language :: Python :: 3.9
Classifier: Programming Language :: Python :: 3.10
Classifier: Programming Language :: Python :: 3.11
Requires-Python: >=3.7
License-File: LICENSE
Requires-Dist: beautifulsoup4>=4.9.3
Requires-Dist: requests>=2.25.1
Requires-Dist: markdownify>=0.11.6
Provides-Extra: dev
Requires-Dist: pytest>=8.0.0; extra == "dev"
Requires-Dist: pytest-cov>=4.1.0; extra == "dev"
Dynamic: license-file
